setup.py
docs/conf.py
docs/_themes/flask_theme_support.py
examples/manage.py
flask_script/__init__.py
flask_script/_compat.py
flask_script/cli.py
flask_script/commands.py
venv/bin/activate_this.py
venv/lib/python3.9/site-packages/_virtualenv.py
venv/lib/python3.9/site-packages/_distutils_hack/__init__.py
venv/lib/python3.9/site-packages/_distutils_hack/override.py
venv/lib/python3.9/site-packages/blinker/__init__.py
venv/lib/python3.9/site-packages/blinker/_saferef.py
venv/lib/python3.9/site-packages/blinker/_utilities.py
venv/lib/python3.9/site-packages/blinker/base.py
venv/lib/python3.9/site-packages/click/__init__.py
venv/lib/python3.9/site-packages/click/_compat.py
venv/lib/python3.9/site-packages/click/_termui_impl.py
venv/lib/python3.9/site-packages/click/_textwrap.py
venv/lib/python3.9/site-packages/click/_winconsole.py
venv/lib/python3.9/site-packages/click/core.py
venv/lib/python3.9/site-packages/click/decorators.py
venv/lib/python3.9/site-packages/click/exceptions.py
venv/lib/python3.9/site-packages/click/formatting.py
venv/lib/python3.9/site-packages/click/globals.py
venv/lib/python3.9/site-packages/click/parser.py
venv/lib/python3.9/site-packages/click/shell_completion.py
venv/lib/python3.9/site-packages/click/termui.py
venv/lib/python3.9/site-packages/click/types.py
venv/lib/python3.9/site-packages/click/utils.py
venv/lib/python3.9/site-packages/flask/__init__.py
venv/lib/python3.9/site-packages/flask/__main__.py
venv/lib/python3.9/site-packages/flask/app.py
venv/lib/python3.9/site-packages/flask/blueprints.py
venv/lib/python3.9/site-packages/flask/cli.py
venv/lib/python3.9/site-packages/flask/config.py
venv/lib/python3.9/site-packages/flask/ctx.py
venv/lib/python3.9/site-packages/flask/debughelpers.py
venv/lib/python3.9/site-packages/flask/globals.py
venv/lib/python3.9/site-packages/flask/helpers.py
venv/lib/python3.9/site-packages/flask/logging.py
venv/lib/python3.9/site-packages/flask/scaffold.py
venv/lib/python3.9/site-packages/flask/sessions.py
flask_script_observable-0.0.6.dist-info/METADATA
flask_script_observable-0.0.6.dist-info/WHEEL
flask_script_observable-0.0.6.dist-info/licenses/LICENSE
flask_script_observable-0.0.6.dist-info/RECORD
