Metadata-Version: 2.1
Name: flask-script-observable
Version: 0.0.6
Summary: A flask-script fork
Project-URL: Homepage, https://github.com/kiandinyari/flask-script
Project-URL: Bug Tracker, https://github.com/smurfix/flask-script/issues
Author-email: Kian Dinyari <kiandinyari@gmail.com>
License-File: LICENSE
Classifier: License :: OSI Approved :: MIT License
Classifier: Operating System :: OS Independent
Classifier: Programming Language :: Python :: 3
Requires-Python: >=3.7
